[
  {
    "type": "section",
    "title": "TABLEOFCONTENTS",
    "items": [
      {
        "title": "Welcome",
        "url": "/page/netexec/README",
        "children": []
      },
      {
        "title": "News",
        "url": "/page/netexec/news",
        "children": [
          {
            "title": "v1.0.0Release!",
            "url": "/page/netexec/news/v1.0.0-release",
            "children": []
          },
          {
            "title": "v1.1.0-nxc4u",
            "url": "/page/netexec/news/v1.1.0-nxc4u",
            "children": []
          },
          {
            "title": "v1.2.0-ItsAlwaysDNS",
            "url": "/page/netexec/news/v1.2.0-ItsAlwaysDNS",
            "children": []
          },
          {
            "title": "v1.3.0-NeedForSpeed",
            "url": "/page/netexec/news/v1.3.0-NeedForSpeed",
            "children": []
          },
          {
            "title": "v1.4.0-SmoothOperator",
            "url": "/page/netexec/news/v1.4.0-SmoothOperator",
            "children": []
          }
        ]
      },
      {
        "title": "NetExecLab",
        "url": "/page/netexec/netexec-lab",
        "children": []
      }
    ]
  },
  {
    "type": "section",
    "title": "GETTINGSTARTED",
    "items": [
      {
        "title": "Installation",
        "url": "/page/netexec/getting-started/installation",
        "children": [
          {
            "title": "InstallationforUnix",
            "url": "/page/netexec/getting-started/installation/installation-on-unix",
            "children": []
          },
          {
            "title": "InstallationforWindows",
            "url": "/page/netexec/getting-started/installation/installation-on-windows",
            "children": []
          },
          {
            "title": "InstallationforMac",
            "url": "/page/netexec/getting-started/installation/installation-for-mac",
            "children": []
          },
          {
            "title": "UsingDocker",
            "url": "/page/netexec/getting-started/installation/using-docker",
            "children": []
          },
          {
            "title": "Manuallybuildingthebinary",
            "url": "/page/netexec/getting-started/installation/manually-building-the-binary",
            "children": []
          },
          {
            "title": "PostInstallationSetup",
            "url": "/page/netexec/getting-started/installation/setting-up-tab-completion",
            "children": []
          }
        ]
      },
      {
        "title": "Selecting&UsingaProtocol",
        "url": "/page/netexec/getting-started/selecting-and-using-a-protocol",
        "children": []
      },
      {
        "title": "TargetFormats",
        "url": "/page/netexec/getting-started/target-formats",
        "children": []
      },
      {
        "title": "UsingCredentials",
        "url": "/page/netexec/getting-started/using-credentials",
        "children": []
      },
      {
        "title": "UsingKerberos",
        "url": "/page/netexec/getting-started/using-kerberos",
        "children": []
      },
      {
        "title": "UsingCertificates",
        "url": "/page/netexec/getting-started/using-certificates",
        "children": []
      },
      {
        "title": "UsingModules",
        "url": "/page/netexec/getting-started/using-modules",
        "children": []
      },
      {
        "title": "DNSoptions",
        "url": "/page/netexec/getting-started/dns-options",
        "children": []
      },
      {
        "title": "DatabaseGeneralUsage",
        "url": "/page/netexec/getting-started/database-general-usage",
        "children": []
      },
      {
        "title": "BloodHoundIntegration",
        "url": "/page/netexec/getting-started/bloodhound-integration",
        "children": []
      },
      {
        "title": "AuditMode",
        "url": "/page/netexec/getting-started/audit-mode",
        "children": []
      },
      {
        "title": "IgnoreOpSecWarnings",
        "url": "/page/netexec/getting-started/ignore-opsec-warnings",
        "children": []
      },
      {
        "title": "Logging",
        "url": "/page/netexec/getting-started/log-your-results",
        "children": []
      }
    ]
  },
  {
    "type": "section",
    "title": "SMBPROTOCOL",
    "items": [
      {
        "title": "Generatehostsfile",
        "url": "/page/netexec/smb-protocol/generate-hosts-file",
        "children": []
      },
      {
        "title": "Generatekrb5.conffile",
        "url": "/page/netexec/smb-protocol/generate-krb5.conf-file",
        "children": []
      },
      {
        "title": "GenerateTGT",
        "url": "/page/netexec/smb-protocol/generate-tgt",
        "children": []
      },
      {
        "title": "ScanforVulnerabilities",
        "url": "/page/netexec/smb-protocol/scan-for-vulnerabilities",
        "children": []
      },
      {
        "title": "Enumeration",
        "url": "/page/netexec/smb-protocol/enumeration",
        "children": [
          {
            "title": "EnumerateHosts",
            "url": "/page/netexec/smb-protocol/enumeration/enumerate-hosts",
            "children": []
          },
          {
            "title": "EnumerateNullSessions",
            "url": "/page/netexec/smb-protocol/enumeration/enumerate-null-sessions",
            "children": []
          },
          {
            "title": "EnumerateGuestLogon",
            "url": "/page/netexec/smb-protocol/enumeration/enumerate-guest-logon",
            "children": []
          },
          {
            "title": "EnumerateHostswithSMBSigningNotRequired",
            "url": "/page/netexec/smb-protocol/enumeration/smb-signing-not-required",
            "children": []
          },
          {
            "title": "EnumerateActiveWindowsSessions",
            "url": "/page/netexec/smb-protocol/enumeration/enumerate-active-windows-sessions",
            "children": []
          },
          {
            "title": "EnumerateLogged-OnUserswiththeRemoteRegistryService",
            "url": "/page/netexec/smb-protocol/enumeration/enumerate-logged-on-users-winreg",
            "children": []
          },
          {
            "title": "EnumerateLogged-OnUserswiththeWorkstationService",
            "url": "/page/netexec/smb-protocol/enumeration/enumerate-logged-on-users-wkssvc",
            "children": []
          },
          {
            "title": "EnumerateSharesandAccess",
            "url": "/page/netexec/smb-protocol/enumeration/enumerate-shares-and-access",
            "children": []
          },
          {
            "title": "EnumerateNetworkInterfaces",
            "url": "/page/netexec/smb-protocol/enumeration/enumerate-network-interfaces",
            "children": []
          },
          {
            "title": "EnumerateNTLMv1",
            "url": "/page/netexec/smb-protocol/enumeration/enumerate-ntlmv1",
            "children": []
          },
          {
            "title": "EnumerateDisks",
            "url": "/page/netexec/smb-protocol/enumeration/enumerate-disks",
            "children": []
          },
          {
            "title": "EnumerateBitlocker",
            "url": "/page/netexec/smb-protocol/enumeration/enumerate-bitlocker",
            "children": []
          },
          {
            "title": "EnumerateDomainUsers",
            "url": "/page/netexec/smb-protocol/enumeration/enumerate-domain-users",
            "children": []
          },
          {
            "title": "EnumerateUsersbyBruteforcingRID",
            "url": "/page/netexec/smb-protocol/enumeration/enumerate-users-by-bruteforcing-rid",
            "children": []
          },
          {
            "title": "EnumerateDomainGroups",
            "url": "/page/netexec/smb-protocol/enumeration/enumerate-domain-groups",
            "children": []
          },
          {
            "title": "EnumerateLocalGroups",
            "url": "/page/netexec/smb-protocol/enumeration/enumerate-local-groups",
            "children": []
          },
          {
            "title": "EnumerateDomainPasswordPolicy",
            "url": "/page/netexec/smb-protocol/enumeration/enumerate-domain-password-policy-1",
            "children": []
          },
          {
            "title": "EnumerateAnti-Virus&EDR",
            "url": "/page/netexec/smb-protocol/enumeration/enumerate-antivirus-edr",
            "children": []
          },
          {
            "title": "Enumerateremoteprocesses",
            "url": "/page/netexec/smb-protocol/enumeration/enumerate-remote-processes",
            "children": []
          },
          {
            "title": "Enumeratechangedlockscreenexecutables",
            "url": "/page/netexec/smb-protocol/enumeration/enumerate-lockscreen-backdoors",
            "children": []
          },
          {
            "title": "EnumeratePrimarySiteServerandDistributionPointviarecon6",
            "url": "/page/netexec/smb-protocol/enumeration/enumerate-sccm-primarysiteserver-and-distributionpoint",
            "children": []
          }
        ]
      },
      {
        "title": "PasswordSpraying",
        "url": "/page/netexec/smb-protocol/password-spraying",
        "children": []
      },
      {
        "title": "Authentication",
        "url": "/page/netexec/smb-protocol/authentication",
        "children": [
          {
            "title": "CheckingCredentials(Domain)",
            "url": "/page/netexec/smb-protocol/authentication/checking-credentials-domain",
            "children": []
          },
          {
            "title": "CheckingCredentials(Local)",
            "url": "/page/netexec/smb-protocol/authentication/checking-credentials-local",
            "children": []
          },
          {
            "title": "Delegation",
            "url": "/page/netexec/smb-protocol/authentication/delegation",
            "children": []
          }
        ]
      },
      {
        "title": "CommandExecution",
        "url": "/page/netexec/smb-protocol/command-execution",
        "children": [
          {
            "title": "ExecutingRemoteCommands",
            "url": "/page/netexec/smb-protocol/command-execution/execute-remote-command",
            "children": [
              {
                "title": "ProcessInjection(pimodule)",
                "url": "/page/netexec/smb-protocol/command-execution/execute-remote-command/process-injection-pi-module",
                "children": []
              }
            ]
          },
          {
            "title": "GettingShells101",
            "url": "/page/netexec/smb-protocol/command-execution/getting-shells-101",
            "children": []
          }
        ]
      },
      {
        "title": "SpideringShares",
        "url": "/page/netexec/smb-protocol/spidering-shares",
        "children": []
      },
      {
        "title": "GetandPutFiles",
        "url": "/page/netexec/smb-protocol/get-and-put-files",
        "children": []
      },
      {
        "title": "ObtainingCredentials",
        "url": "/page/netexec/smb-protocol/obtaining-credentials",
        "children": [
          {
            "title": "DumpSAM",
            "url": "/page/netexec/smb-protocol/obtaining-credentials/dump-sam",
            "children": []
          },
          {
            "title": "DumpLSA",
            "url": "/page/netexec/smb-protocol/obtaining-credentials/dump-lsa",
            "children": []
          },
          {
            "title": "DumpNTDS.dit",
            "url": "/page/netexec/smb-protocol/obtaining-credentials/dump-ntds.dit",
            "children": []
          },
          {
            "title": "DumpLSASS",
            "url": "/page/netexec/smb-protocol/obtaining-credentials/dump-lsass",
            "children": []
          },
          {
            "title": "DumpDPAPI",
            "url": "/page/netexec/smb-protocol/obtaining-credentials/dump-dpapi",
            "children": []
          },
          {
            "title": "DumpwithBackupOperatorPriv",
            "url": "/page/netexec/smb-protocol/obtaining-credentials/dump-backupop",
            "children": []
          },
          {
            "title": "DumpSCCM",
            "url": "/page/netexec/smb-protocol/obtaining-credentials/dump-sccm",
            "children": []
          },
          {
            "title": "DumpTokenBrokerCache",
            "url": "/page/netexec/smb-protocol/obtaining-credentials/dump-token-broker-cache",
            "children": []
          },
          {
            "title": "DumpWIFIpassword",
            "url": "/page/netexec/smb-protocol/obtaining-credentials/dump-wifi-password",
            "children": []
          },
          {
            "title": "DumpKeePass",
            "url": "/page/netexec/smb-protocol/obtaining-credentials/dump-keepass",
            "children": []
          },
          {
            "title": "DumpVeeam",
            "url": "/page/netexec/smb-protocol/obtaining-credentials/dump-veeam",
            "children": []
          },
          {
            "title": "DumpWinSCP",
            "url": "/page/netexec/smb-protocol/obtaining-credentials/dump-winscp",
            "children": []
          },
          {
            "title": "DumpPuTTY",
            "url": "/page/netexec/smb-protocol/obtaining-credentials/dump-putty",
            "children": []
          },
          {
            "title": "DumpVNC",
            "url": "/page/netexec/smb-protocol/obtaining-credentials/dump-vnc",
            "children": []
          },
          {
            "title": "DumpmRemoteNG",
            "url": "/page/netexec/smb-protocol/obtaining-credentials/dump-mremoteng",
            "children": []
          },
          {
            "title": "DumpNotepad",
            "url": "/page/netexec/smb-protocol/obtaining-credentials/dump-notepad",
            "children": []
          },
          {
            "title": "DumpNotepad++",
            "url": "/page/netexec/smb-protocol/obtaining-credentials/dump-notepad++",
            "children": []
          },
          {
            "title": "DumpRemoteDesktopCredentialManager",
            "url": "/page/netexec/smb-protocol/obtaining-credentials/dump-rdcman",
            "children": []
          },
          {
            "title": "DumpEventLogCreds(4688)",
            "url": "/page/netexec/smb-protocol/obtaining-credentials/eventlog-creds",
            "children": []
          }
        ]
      },
      {
        "title": "DefeatingLAPS",
        "url": "/page/netexec/smb-protocol/defeating-laps",
        "children": []
      },
      {
        "title": "CheckingforSpooler&WebDav",
        "url": "/page/netexec/smb-protocol/spooler-webdav-running",
        "children": []
      },
      {
        "title": "StealMicrosoftTeamsCookies",
        "url": "/page/netexec/smb-protocol/steal-microsoft-teams-cookies",
        "children": []
      },
      {
        "title": "Impersonatelogged-onUsers",
        "url": "/page/netexec/smb-protocol/impersonate-logged-on-users",
        "children": []
      },
      {
        "title": "ChangeUserPassword",
        "url": "/page/netexec/smb-protocol/change-user-password",
        "children": []
      },
      {
        "title": "ModifyGroup",
        "url": "/page/netexec/smb-protocol/modify-group",
        "children": []
      },
      {
        "title": "DumpUserLocalSecurityQuestions",
        "url": "/page/netexec/smb-protocol/dump-user-local-security-questions",
        "children": []
      }
    ]
  },
  {
    "type": "section",
    "title": "LDAPPROTOCOL",
    "items": [
      {
        "title": "Authentication",
        "url": "/page/netexec/ldap-protocol/authentication",
        "children": []
      },
      {
        "title": "EnumerateDomainUsers",
        "url": "/page/netexec/ldap-protocol/enumerate-users",
        "children": []
      },
      {
        "title": "EnumerateDomainGroups",
        "url": "/page/netexec/ldap-protocol/enumerate-group-members",
        "children": []
      },
      {
        "title": "QueryLDAP",
        "url": "/page/netexec/ldap-protocol/query-ldap",
        "children": []
      },
      {
        "title": "ASREPRoast",
        "url": "/page/netexec/ldap-protocol/asreproast",
        "children": []
      },
      {
        "title": "FindDomainSID",
        "url": "/page/netexec/ldap-protocol/find-domain-sid",
        "children": []
      },
      {
        "title": "Kerberoasting",
        "url": "/page/netexec/ldap-protocol/kerberoasting",
        "children": []
      },
      {
        "title": "FindMisconfiguredDelegation",
        "url": "/page/netexec/ldap-protocol/find-misconfigured-delegation",
        "children": []
      },
      {
        "title": "UnconstrainedDelegation",
        "url": "/page/netexec/ldap-protocol/unconstrained-delegation",
        "children": []
      },
      {
        "title": "AdminCount",
        "url": "/page/netexec/ldap-protocol/admin-count",
        "children": []
      },
      {
        "title": "MachineAccountQuota",
        "url": "/page/netexec/ldap-protocol/machine-account-quota",
        "children": []
      },
      {
        "title": "GetUserDescriptions",
        "url": "/page/netexec/ldap-protocol/get-user-descriptions",
        "children": []
      },
      {
        "title": "DumpgMSA",
        "url": "/page/netexec/ldap-protocol/dump-gmsa",
        "children": []
      },
      {
        "title": "Pre2kComputerAccountAbuse",
        "url": "/page/netexec/ldap-protocol/pre2k",
        "children": []
      },
      {
        "title": "ExploitESC8(ADCS)",
        "url": "/page/netexec/ldap-protocol/exploit-esc8-adcs",
        "children": []
      },
      {
        "title": "ExtractSubnet",
        "url": "/page/netexec/ldap-protocol/extract-subnet",
        "children": []
      },
      {
        "title": "CheckLDAPSigning",
        "url": "/page/netexec/ldap-protocol/check-ldap-signing",
        "children": []
      },
      {
        "title": "ReadDACLRights",
        "url": "/page/netexec/ldap-protocol/read-dacl-right",
        "children": []
      },
      {
        "title": "ExtractgMSASecrets",
        "url": "/page/netexec/ldap-protocol/extract-gmsa-secrets",
        "children": []
      },
      {
        "title": "BloodhoundIngestor",
        "url": "/page/netexec/ldap-protocol/bloodhound-ingestor",
        "children": []
      },
      {
        "title": "ListDCIP/EnumTrust",
        "url": "/page/netexec/ldap-protocol/dc-list",
        "children": []
      },
      {
        "title": "AbuseDomainTrust:Raisechild",
        "url": "/page/netexec/ldap-protocol/raisechild",
        "children": []
      },
      {
        "title": "EnumerateDomainTrusts",
        "url": "/page/netexec/ldap-protocol/enumerate-trusts",
        "children": []
      },
      {
        "title": "EnumerateSCCM",
        "url": "/page/netexec/ldap-protocol/enumerate-sccm",
        "children": []
      },
      {
        "title": "EnumerateEntraID",
        "url": "/page/netexec/ldap-protocol/enumerate-entra-id",
        "children": []
      },
      {
        "title": "DumpPSO",
        "url": "/page/netexec/dump-pso",
        "children": []
      },
      {
        "title": "EnumeratescriptPath",
        "url": "/page/netexec/ldap-protocol/get-scriptpath",
        "children": []
      },
      {
        "title": "EnumerateUnsecureDNSZones",
        "url": "/page/netexec/ldap-protocol/enumerate-unsecure-dns-zones",
        "children": []
      }
    ]
  },
  {
    "type": "section",
    "title": "WINRMPROTOCOL",
    "items": [
      {
        "title": "PasswordSpraying",
        "url": "/page/netexec/winrm-protocol/password-spraying",
        "children": []
      },
      {
        "title": "Authentication",
        "url": "/page/netexec/winrm-protocol/authentication",
        "children": []
      },
      {
        "title": "CommandExecution",
        "url": "/page/netexec/winrm-protocol/command-execution",
        "children": []
      },
      {
        "title": "DefeatingLAPS",
        "url": "/page/netexec/winrm-protocol/defeating-laps",
        "children": []
      },
      {
        "title": "ObtainingCredentials",
        "url": "/page/netexec/winrm-protocol/obtaining-credentials",
        "children": [
          {
            "title": "DumpSAM",
            "url": "/page/netexec/winrm-protocol/obtaining-credentials/dump-sam",
            "children": []
          },
          {
            "title": "DumpLSA",
            "url": "/page/netexec/winrm-protocol/obtaining-credentials/dump-lsa",
            "children": []
          },
          {
            "title": "DumpDPAPI",
            "url": "/page/netexec/winrm-protocol/obtaining-credentials/dump-dpapi",
            "children": []
          }
        ]
      }
    ]
  },
  {
    "type": "section",
    "title": "MSSQLPROTOCOL",
    "items": [
      {
        "title": "Enumeration",
        "url": "/page/netexec/mssql-protocol/enumeration",
        "children": [
          {
            "title": "Enumeratingencryptionsettings",
            "url": "/page/netexec/mssql-protocol/enumeration/enumerating-encryption-settings",
            "children": []
          },
          {
            "title": "EnumeratingChannelBindingconfiguration",
            "url": "/page/netexec/mssql-protocol/enumeration/enumerating-channel-binding-configuration",
            "children": []
          }
        ]
      },
      {
        "title": "PasswordSpraying",
        "url": "/page/netexec/mssql-protocol/mssql-passwordspray",
        "children": []
      },
      {
        "title": "Authentication",
        "url": "/page/netexec/mssql-protocol/authentication",
        "children": []
      },
      {
        "title": "MSSQLPrivEsc",
        "url": "/page/netexec/mssql-protocol/mssql-privesc",
        "children": []
      },
      {
        "title": "MSSQLCommandExecution",
        "url": "/page/netexec/mssql-protocol/mssql-command",
        "children": []
      },
      {
        "title": "MSSQLUpload&Download",
        "url": "/page/netexec/mssql-protocol/mssql-upload-download",
        "children": []
      },
      {
        "title": "Executeviaxp\\_cmdshell",
        "url": "/page/netexec/mssql-protocol/windows-command",
        "children": []
      },
      {
        "title": "EnumerateUsersbyBruteforcingRID",
        "url": "/page/netexec/mssql-protocol/enumerate-users-by-bruteforcing-rid",
        "children": []
      },
      {
        "title": "MSSQLLinkedServers",
        "url": "/page/netexec/mssql-protocol/mssql-linked-servers",
        "children": []
      }
    ]
  },
  {
    "type": "section",
    "title": "SSHPROTOCOL",
    "items": [
      {
        "title": "PasswordSpraying",
        "url": "/page/netexec/ssh-protocol/password-spraying",
        "children": []
      },
      {
        "title": "Authentication",
        "url": "/page/netexec/ssh-protocol/authentication",
        "children": []
      },
      {
        "title": "CommandExecution",
        "url": "/page/netexec/ssh-protocol/command-execution",
        "children": []
      },
      {
        "title": "GetandPutFiles",
        "url": "/page/netexec/ssh-protocol/get-and-put-files",
        "children": []
      }
    ]
  },
  {
    "type": "section",
    "title": "FTPPROTOCOL",
    "items": [
      {
        "title": "PasswordSpraying",
        "url": "/page/netexec/ftp-protocol/password-spraying",
        "children": []
      },
      {
        "title": "FileListing,etc",
        "url": "/page/netexec/ftp-protocol/file-listing-etc",
        "children": []
      },
      {
        "title": "FileUpload&Download",
        "url": "/page/netexec/ftp-protocol/get-and-put-files",
        "children": []
      }
    ]
  },
  {
    "type": "section",
    "title": "RDPPROTOCOL",
    "items": [
      {
        "title": "PasswordSpraying",
        "url": "/page/netexec/rdp-protocol/password-spraying",
        "children": []
      },
      {
        "title": "Screenshot(connected)",
        "url": "/page/netexec/rdp-protocol/screenshot-connected",
        "children": []
      },
      {
        "title": "ScreenshotWithoutNLA(notconnected)",
        "url": "/page/netexec/rdp-protocol/screenshot-without-nla-not-connected",
        "children": []
      },
      {
        "title": "CommandExecution",
        "url": "/page/netexec/rdp-protocol/command-execution",
        "children": []
      }
    ]
  },
  {
    "type": "section",
    "title": "WMIPROTOCOL",
    "items": [
      {
        "title": "PasswordSpraying",
        "url": "/page/netexec/wmi-protocol/password-spraying",
        "children": []
      },
      {
        "title": "Authentication",
        "url": "/page/netexec/wmi-protocol/authentication",
        "children": []
      },
      {
        "title": "CommandExecution",
        "url": "/page/netexec/wmi-protocol/command-execution",
        "children": []
      }
    ]
  },
  {
    "type": "section",
    "title": "NFSPROTOCOL",
    "items": [
      {
        "title": "Enumeration",
        "url": "/page/netexec/nfs-protocol/Enumeration",
        "children": []
      },
      {
        "title": "DownloadandUploadFiles",
        "url": "/page/netexec/nfs-protocol/Download-and-Upload-Files",
        "children": []
      },
      {
        "title": "Chmod",
        "url": "/page/netexec/nfs-protocol/chmod",
        "children": []
      },
      {
        "title": "Escapetorootfilesystem",
        "url": "/page/netexec/nfs-protocol/escape-to-root-file-system",
        "children": []
      }
    ]
  },
  {
    "type": "section",
    "title": "VNCPROTOCOL",
    "items": [
      {
        "title": "Authentication",
        "url": "/page/netexec/vnc-protocol/authentication",
        "children": []
      }
    ]
  }
]